CHANGES
LICENSE
MANIFEST.in
README.rst
setup.py
sbl2py/__init__.py
sbl2py/__main__.py
sbl2py/ast.py
sbl2py/grammar.py
sbl2py/utils.py
sbl2py.egg-info/PKG-INFO
sbl2py.egg-info/SOURCES.txt
sbl2py.egg-info/dependency_links.txt
sbl2py.egg-info/entry_points.txt
sbl2py.egg-info/requires.txt
sbl2py.egg-info/top_level.txt