Metadata-Version: 1.1
Name: sbl2py
Version: 0.1.0
Summary: A Snowball-to-Python compiler
Home-page: https://github.com/torfuspolymorphus/sbl2py
Author: Florian Brucker
Author-email: mail@florianbrucker.de
License: MIT
Keywords: snowball compiler
Platform: UNKNOWN
Classifier: Development Status :: 4 - Beta
Classifier: Intended Audience :: Developers
Classifier: Topic :: Software Development :: Code Generators
Classifier: Topic :: Software Development :: Compilers
Classifier: Topic :: Text Processing :: Linguistic
Classifier: License :: OSI Approved :: MIT License
Classifier: Programming Language :: Python :: 2
Classifier: Programming Language :: Python :: 2.7
